AUTHORS.rst
CHANGES.rst
MANIFEST.in
README.rst
requirements-testing.txt
setup.py
tox.ini
pytest_cloud/__init__.py
pytest_cloud/patches.py
pytest_cloud/plugin.py
pytest_cloud/rsync.py
pytest_cloud.egg-info/PKG-INFO
pytest_cloud.egg-info/SOURCES.txt
pytest_cloud.egg-info/dependency_links.txt
pytest_cloud.egg-info/entry_points.txt
pytest_cloud.egg-info/pbr.json
pytest_cloud.egg-info/requires.txt
pytest_cloud.egg-info/top_level.txt